["```py\n{\n  \"title\": \"Mobility\",\n  \"scopes\": [\n    {\n      \"level\": \"Scope 1\",\n      \"list\": [\n        {\n          \"type\": \"component\",\n          \"consumer\": {\n            \"name\": \"Volkswagen Golf (2014)\",\n            \"description\": \"Engine ID 45, 4 cylinders, Manual 6-spd\",\n            \"consumptions\": {\n              \"diesel\": {\n                \"value\": \"0.0735046875\",\n                \"unit\": \"l\",\n                \"base_unit\": \"km\",\n                \"reference_url\": \"https://www.fueleconomy.gov/\"\n              }\n            }\n          },\n          \"quantity\": \"10000\",\n          \"quantity_unit\": \"km\",\n          \"source\": {\n            \"name\": \"Gas/Diesel oil\",\n            \"type\": \"diesel\",\n            \"emissions\": {\n              \"co2e\": {\n                \"value\": \"3.25\",\n                \"unit\": \"kg\",\n                \"base_unit\": \"l\",\n                \"reference_url\": \"https://bilansges.ademe.fr/index.htm?new_liquides.htm\"\n              }\n            }\n          }\n        }\n      ]\n    }\n  ]\n}\n```"]